OCRLibrary/__init__.py
OCRLibrary/version.py
OCRLibrary/keywords/__init__.py
OCRLibrary/keywords/binary_image_transformation.py
OCRLibrary/keywords/changing_colourspace_transformation.py
OCRLibrary/keywords/content_location.py
OCRLibrary/keywords/content_validation.py
OCRLibrary/keywords/read_and_save_images.py
OCRLibrary/keywords/smoothing_image_transformation.py
OCRLibrary/utils/__init__.py
OCRLibrary/utils/exceptions/__init__.py
OCRLibrary/utils/exceptions/exception_handler.py
OCRLibrary/utils/exceptions/exceptions.py
OCRLibrary/utils/helpers/__init__.py
OCRLibrary/utils/helpers/logging.py
OCRLibrary/utils/helpers/robot_conversions.py
OCRLibrary/utils/imageprocessing/__init__.py
OCRLibrary/utils/imageprocessing/image_processing_colour.py
OCRLibrary/utils/imageprocessing/image_processing_generic.py
OCRLibrary/utils/imageprocessing/image_processing_gray.py
OCRLibrary/utils/imageprocessing/imagetransformation/__init__.py
OCRLibrary/utils/imageprocessing/imagetransformation/changing_colourspaces.py
OCRLibrary/utils/imageprocessing/imagetransformation/image_smoothing.py
OCRLibrary/utils/imageprocessing/imagetransformation/image_thresholding.py
OCRLibrary/utils/imageprocessing/imagetransformation/morphological_transformations.py
OCRLibrary/utils/imageprocessing/imagetransformation/structuring_element.py
OCRLibrary/utils/imagereading/__init__.py
OCRLibrary/utils/imagereading/image_reading.py
OCRLibrary/utils/imagereading/text_locating.py
tests/__init__.py
tests/test_binary_image_transformation_keywords.py
tests/test_changing_colourspace_tranformation_keywords.py
tests/test_content_location_keywords.py
tests/test_content_validation_keywords.py
tests/test_read_and_save_images_keywords.py
tests/test_smoothing_image_transformation_keywords.py
robotframework_ocrlibrary-2.0.0.dist-info/LICENSE
robotframework_ocrlibrary-2.0.0.dist-info/METADATA
robotframework_ocrlibrary-2.0.0.dist-info/WHEEL
robotframework_ocrlibrary-2.0.0.dist-info/top_level.txt
robotframework_ocrlibrary-2.0.0.dist-info/RECORD
