Metadata-Version: 2.1
Name: robotframework-ocrlibrary
Version: 2.0.0
Summary: A robot framework library that utilizes OpenCV image processing and pytesseract OCR.
Home-page: https://github.com/bendurston/robotframework-ocrlibrary
Author: Ben Durston
Author-email: bengdurston@gmail.com
License: UNKNOWN
Project-URL: Bug Tracker, https://github.com/bendurston/robotframework-ocrlibrary/issues
Platform: UNKNOWN
Classifier: Programming Language :: Python
Classifier: Programming Language :: Python :: 3.6
Classifier: Programming Language :: Python :: 3.7
Classifier: Programming Language :: Python :: 3.8
Classifier: Programming Language :: Python :: 3.9
Classifier: License :: OSI Approved :: Apache Software License
Classifier: Operating System :: OS Independent
Requires-Python: >=3.6
License-File: LICENSE
Requires-Dist: robotframework (>=3.0)
Requires-Dist: opencv-python (>=4.0.0.21)
Requires-Dist: pytesseract (>=0.3.8)
Requires-Dist: numpy (>=1.19.3)
